urldt/__init__.py
urldt/__main__.py
urldt/__version__.py
urldt/cli.py
urldt/scanner.py
urldt/url_asset.py
urldt/utils.py
urldt-1.0.0.dist-info/LICENSE
urldt-1.0.0.dist-info/METADATA
urldt-1.0.0.dist-info/WHEEL
urldt-1.0.0.dist-info/entry_points.txt
urldt-1.0.0.dist-info/top_level.txt
urldt-1.0.0.dist-info/RECORD
