Metadata-Version: 2.1
Name: urldt
Version: 1.0.0
Summary: Detect if url is available.
Author-email: Yingjie Shang <me@shangcode.cn>
License: MIT License        
Project-URL: Homepage, https://github.com/shangcode/urldt
Keywords: cyber security,network,url,detect,available
Classifier: License :: OSI Approved :: MIT License
Classifier: Programming Language :: Python :: 3
Classifier: Operating System :: OS Independent
Requires-Python: >=3.9
License-File: LICENSE
Requires-Dist: certifi (>=2022.6.15)
Requires-Dist: charset-normalizer (>=2.1.0)
Requires-Dist: idna (>=3.3)
Requires-Dist: requests (>=2.28.1)
Requires-Dist: toml (>=0.10.2)
Requires-Dist: urllib3 (>=1.26.11)
Provides-Extra: dev
Requires-Dist: autopep8 ; extra == 'dev'
Requires-Dist: pycodestyle ; extra == 'dev'
Requires-Dist: pip-tools ; extra == 'dev'
Requires-Dist: pytest ; extra == 'dev'
